MANIFEST.in
README.rst
setup.cfg
setup.py
dynamo_objects/__init__.py
dynamo_objects/database.py
dynamo_objects/dynamock.py
dynamo_objects/memorydb.py
dynamo_objects.egg-info/PKG-INFO
dynamo_objects.egg-info/SOURCES.txt
dynamo_objects.egg-info/dependency_links.txt
dynamo_objects.egg-info/requires.txt
dynamo_objects.egg-info/top_level.txt