Metadata-Version: 1.1
Name: dynamo-objects
Version: 1.0.9
Summary: Simple DynamoDB object mapper and utils
Home-page: https://github.com/serebrov/dynamo_objects
Author: Boris Serebrov
Author-email: dynamo_objects@googlegroups.com
License: MIT
Keywords: python dynamodb orm odm
Platform: UNKNOWN
Classifier: Development Status :: 4 - Beta
Classifier: Intended Audience :: Developers
Classifier: Programming Language :: Python
Classifier: Operating System :: OS Independent
Classifier: Programming Language :: Python :: 2.7
Classifier: Programming Language :: Python :: 3.3
Classifier: Programming Language :: Python :: 3.4
Classifier: License :: OSI Approved :: MIT License
Classifier: Topic :: Database
